{
  "createdAt": "2019-12-12T11:12:12.000Z",
  "lastModifiedAt": "2019-12-12T11:12:12.000Z",
  "id": "test-id",
  "version": 1,
  "parent": {
    "id": "test-id",
    "typeId": "category"
  },
  "custom": {
    "fields": {
      "test-key": {
        "val": "test-string"
      }
    },
    "type": {
      "id": "test-id",
      "typeId": "type"
    }
  },
  "externalId": "test-id",
  "description": {
    "test-key": "test-value"
  },
  "metaDescription": {
    "test-key": "test-value"
  },
  "assets": [
    {
      "sources": [
        {
          "contentType": "application/json",
          "uri": "https://commercetools.com",
          "dimensions": {
            "w": 5,
            "h": 10
          }
        }
      ],
      "custom": {
        "fields": {
          "test-key": {
            "val": "test-string"
          }
        },
        "type": {
          "id": "test-id",
          "typeId": "type"
        }
      },
      "name": {
        "test-key": "test-value"
      },
      "description": {
        "test-key": "test-value"
      },
      "id": "test-id",
      "key": "test-key",
      "tags": [
        "tag 1",
        "tag 2"
      ]
    }
  ],
  "metaKeywords": {
    "test-key": "test-value"
  },
  "orderHint": "test-string",
  "metaTitle": {
    "test-key": "test-value"
  },
  "name": {
    "test-key": "test-value"
  },
  "ancestors": [
    {
      "id": "test-id",
      "typeId": "category"
    }
  ],
  "key": "test-key",
  "slug": {
    "test-key": "test-value"
  }
}
